schemaflow/__init__.py
schemaflow/exceptions.py
schemaflow/ops.py
schemaflow/pipe.py
schemaflow/pipeline.py
schemaflow/types.py
schemaflow/tests/__init__.py
schemaflow/tests/test_array.py
schemaflow/tests/test_complete.py
schemaflow/tests/test_container.py
schemaflow/tests/test_pandas_df.py
schemaflow/tests/test_pipe.py
schemaflow/tests/test_pipeline.py
schemaflow/tests/test_pipeline_pandas_df.py
schemaflow/tests/test_pyspark_df.py
schemaflow-0.2.0.dist-info/METADATA
schemaflow-0.2.0.dist-info/RECORD
schemaflow-0.2.0.dist-info/WHEEL
schemaflow-0.2.0.dist-info/top_level.txt
tests/__init__.py
tests/test_array.py
tests/test_container.py
tests/test_pandas_df.py
tests/test_pipe.py
tests/test_pipeline.py
tests/test_pipeline_pandas_df.py
tests/test_pyspark_df.py
