Metadata-Version: 2.1
Name: schemaflow
Version: 0.2.0
Summary: A package to write schema-aware data pipelines
Home-page: https://github.com/jorgecarleitao/schemaflow
Author: Jorge C. Leitao
License: UNKNOWN
Platform: UNKNOWN
Classifier: Programming Language :: Python :: 3
Classifier: License :: OSI Approved :: MIT License
Classifier: Operating System :: OS Independent
